LICENSE
MANIFEST.in
README.rst
setup.cfg
setup.py
yarn_api_client/__init__.py
yarn_api_client/__main__.py
yarn_api_client/application_master.py
yarn_api_client/base.py
yarn_api_client/constants.py
yarn_api_client/errors.py
yarn_api_client/hadoop_conf.py
yarn_api_client/history_server.py
yarn_api_client/main.py
yarn_api_client/node_manager.py
yarn_api_client/resource_manager.py
yarn_api_client/timeline_server.py
yarn_api_client_kenny.egg-info/PKG-INFO
yarn_api_client_kenny.egg-info/SOURCES.txt
yarn_api_client_kenny.egg-info/dependency_links.txt
yarn_api_client_kenny.egg-info/entry_points.txt
yarn_api_client_kenny.egg-info/requires.txt
yarn_api_client_kenny.egg-info/top_level.txt