Metadata-Version: 1.1
Name: yarn-api-client-kenny
Version: 0.3.2
Summary: Python client for Hadoop® YARN API
Home-page: https://github.com/71nn/hadoop-yarn-api-python-client
Author: Kenny Liu
Author-email: liuzihao1@wps.cn
License: BSD
Platform: UNKNOWN
Classifier: Development Status :: 4 - Beta
Classifier: Intended Audience :: Developers
Classifier: License :: OSI Approved :: BSD License
Classifier: Operating System :: OS Independent
Classifier: Programming Language :: Python :: 2.6
Classifier: Programming Language :: Python :: 2.7
Classifier: Programming Language :: Python :: 3.5
Classifier: Programming Language :: Python :: 3.6
Classifier: Topic :: System :: Distributed Computing
